dragon_ml_toolbox-20.14.0.dist-info/licenses/LICENSE
dragon_ml_toolbox-20.14.0.dist-info/licenses/LICENSE-THIRD-PARTY.md
ml_tools/__init__.py
ml_tools/constants.py
ml_tools/ETL_cleaning/__init__.py
ml_tools/ETL_cleaning/_basic_clean.py
ml_tools/ETL_cleaning/_clean_tools.py
ml_tools/ETL_cleaning/_dragon_cleaner.py
ml_tools/ETL_engineering/__init__.py
ml_tools/ETL_engineering/_dragon_engineering.py
ml_tools/ETL_engineering/_transforms.py
ml_tools/GUI_tools/_GUI_tools.py
ml_tools/GUI_tools/__init__.py
ml_tools/IO_tools/_IO_loggers.py
ml_tools/IO_tools/_IO_save_load.py
ml_tools/IO_tools/_IO_utils.py
ml_tools/IO_tools/__init__.py
ml_tools/MICE/_MICE_imputation.py
ml_tools/MICE/__init__.py
ml_tools/MICE/_dragon_mice.py
ml_tools/ML_callbacks/__init__.py
ml_tools/ML_callbacks/_base.py
ml_tools/ML_callbacks/_checkpoint.py
ml_tools/ML_callbacks/_early_stop.py
ml_tools/ML_callbacks/_scheduler.py
ml_tools/ML_chain/__init__.py
ml_tools/ML_chain/_chaining_tools.py
ml_tools/ML_chain/_dragon_chain.py
ml_tools/ML_chain/_update_schema.py
ml_tools/ML_configuration/__init__.py
ml_tools/ML_configuration/_base_model_config.py
ml_tools/ML_configuration/_finalize.py
ml_tools/ML_configuration/_metrics.py
ml_tools/ML_configuration/_models.py
ml_tools/ML_configuration/_training.py
ml_tools/ML_datasetmaster/__init__.py
ml_tools/ML_datasetmaster/_base_datasetmaster.py
ml_tools/ML_datasetmaster/_datasetmaster.py
ml_tools/ML_datasetmaster/_sequence_datasetmaster.py
ml_tools/ML_datasetmaster/_vision_datasetmaster.py
ml_tools/ML_evaluation/__init__.py
ml_tools/ML_evaluation/_classification.py
ml_tools/ML_evaluation/_feature_importance.py
ml_tools/ML_evaluation/_helpers.py
ml_tools/ML_evaluation/_loss.py
ml_tools/ML_evaluation/_regression.py
ml_tools/ML_evaluation/_sequence.py
ml_tools/ML_evaluation/_vision.py
ml_tools/ML_evaluation_captum/_ML_evaluation_captum.py
ml_tools/ML_evaluation_captum/__init__.py
ml_tools/ML_finalize_handler/_ML_finalize_handler.py
ml_tools/ML_finalize_handler/__init__.py
ml_tools/ML_inference/__init__.py
ml_tools/ML_inference/_base_inference.py
ml_tools/ML_inference/_chain_inference.py
dragon_ml_toolbox-20.14.0.dist-info/METADATA
dragon_ml_toolbox-20.14.0.dist-info/WHEEL
dragon_ml_toolbox-20.14.0.dist-info/top_level.txt
dragon_ml_toolbox-20.14.0.dist-info/RECORD
