Metadata-Version: 2.4
Name: dragon-ml-toolbox
Version: 20.14.0
Summary: Complete pipelines and helper tools for data science and machine learning projects.
Author-email: Karl Luigi Loza Vidaurre <luigiloza@gmail.com>
License-Expression: MIT
Project-URL: Homepage, https://github.com/DrAg0n-BoRn/ML_tools
Project-URL: Changelog, https://github.com/DrAg0n-BoRn/ML_tools/blob/master/CHANGELOG.md
Classifier: Programming Language :: Python :: 3
Classifier: Operating System :: OS Independent
Requires-Python: ==3.12.*
License-File: LICENSE
License-File: LICENSE-THIRD-PARTY.md
Provides-Extra: ml
Requires-Dist: torch; extra == "ml"
Requires-Dist: torchvision; extra == "ml"
Requires-Dist: numpy<2.0; extra == "ml"
Requires-Dist: pandas; extra == "ml"
Requires-Dist: polars>=1.0; extra == "ml"
Requires-Dist: pyarrow; extra == "ml"
Requires-Dist: joblib; extra == "ml"
Requires-Dist: tqdm; extra == "ml"
Requires-Dist: colorlog; extra == "ml"
Requires-Dist: scikit-learn; extra == "ml"
Requires-Dist: shap; extra == "ml"
Requires-Dist: captum; extra == "ml"
Requires-Dist: evotorch; extra == "ml"
Requires-Dist: torchmetrics; extra == "ml"
Requires-Dist: matplotlib; extra == "ml"
Requires-Dist: seaborn; extra == "ml"
Requires-Dist: plotly; extra == "ml"
Requires-Dist: Pillow; extra == "ml"
Requires-Dist: ipython; extra == "ml"
Requires-Dist: ipykernel; extra == "ml"
Requires-Dist: notebook; extra == "ml"
Requires-Dist: jupyterlab; extra == "ml"
Requires-Dist: ipywidgets; extra == "ml"
Provides-Extra: ensemble
Requires-Dist: numpy; extra == "ensemble"
Requires-Dist: numba>=0.60; extra == "ensemble"
Requires-Dist: shap>=0.46; extra == "ensemble"
Requires-Dist: pandas; extra == "ensemble"
Requires-Dist: polars>=1.0; extra == "ensemble"
Requires-Dist: pyarrow; extra == "ensemble"
Requires-Dist: joblib; extra == "ensemble"
Requires-Dist: tqdm; extra == "ensemble"
Requires-Dist: colorlog; extra == "ensemble"
Requires-Dist: scikit-learn<1.8,>=1.5; extra == "ensemble"
Requires-Dist: imbalanced-learn; extra == "ensemble"
Requires-Dist: xgboost; extra == "ensemble"
Requires-Dist: lightgbm; extra == "ensemble"
Requires-Dist: matplotlib; extra == "ensemble"
Requires-Dist: seaborn; extra == "ensemble"
Requires-Dist: ipython; extra == "ensemble"
Requires-Dist: ipykernel; extra == "ensemble"
Requires-Dist: notebook; extra == "ensemble"
Requires-Dist: jupyterlab; extra == "ensemble"
Requires-Dist: ipywidgets; extra == "ensemble"
Provides-Extra: mice
Requires-Dist: numpy<2.0; extra == "mice"
Requires-Dist: pandas; extra == "mice"
Requires-Dist: polars>=1.0; extra == "mice"
Requires-Dist: joblib; extra == "mice"
Requires-Dist: miceforest>=6.0.0; extra == "mice"
Requires-Dist: plotnine>=0.12; extra == "mice"
Requires-Dist: matplotlib; extra == "mice"
Requires-Dist: statsmodels; extra == "mice"
Requires-Dist: lightgbm<=4.5.0; extra == "mice"
Requires-Dist: shap; extra == "mice"
Requires-Dist: colorlog; extra == "mice"
Requires-Dist: pyarrow; extra == "mice"
Provides-Extra: excel
Requires-Dist: pandas; extra == "excel"
Requires-Dist: openpyxl; extra == "excel"
Requires-Dist: ipython; extra == "excel"
Requires-Dist: ipykernel; extra == "excel"
Requires-Dist: notebook; extra == "excel"
Requires-Dist: jupyterlab; extra == "excel"
Requires-Dist: ipywidgets; extra == "excel"
Requires-Dist: colorlog; extra == "excel"
Provides-Extra: gui-boost
Requires-Dist: numpy; extra == "gui-boost"
Requires-Dist: joblib; extra == "gui-boost"
Requires-Dist: FreeSimpleGUI>=5.2; extra == "gui-boost"
Requires-Dist: xgboost; extra == "gui-boost"
Requires-Dist: lightgbm; extra == "gui-boost"
Provides-Extra: gui-torch
Requires-Dist: numpy<2.0; extra == "gui-torch"
Requires-Dist: torch; extra == "gui-torch"
Requires-Dist: FreeSimpleGUI>=5.2; extra == "gui-torch"
Dynamic: license-file
